merge_guard/__init__.py
merge_guard/cli.py
merge_guard/detector.py
merge_guard/formatters.py
merge_guard/git_utils.py
merge_guard/models.py
merge_guard/py.typed
merge_guard-0.1.0.dist-info/WHEEL
merge_guard-0.1.0.dist-info/entry_points.txt
merge_guard-0.1.0.dist-info/METADATA
merge_guard-0.1.0.dist-info/RECORD
