Metadata-Version: 2.3
Name: merge-guard
Version: 0.1.0
Summary: A Git pre-commit hook that detects AI-generated code patterns and prevents low-quality code from being committed
Keywords: git,pre-commit,code-quality,ai,linter,static-analysis,code-review
Author: Ashalesh Tilawat
Author-email: Ashalesh Tilawat <ashtilawat23@gmail.com>
License: Proprietary
Classifier: Development Status :: 4 - Beta
Classifier: Intended Audience :: Developers
Classifier: License :: Other/Proprietary License
Classifier: Programming Language :: Python :: 3
Classifier: Programming Language :: Python :: 3.9
Classifier: Programming Language :: Python :: 3.10
Classifier: Programming Language :: Python :: 3.11
Classifier: Programming Language :: Python :: 3.12
Classifier: Programming Language :: Python :: 3.13
Classifier: Topic :: Software Development :: Quality Assurance
Classifier: Topic :: Software Development :: Version Control :: Git
Classifier: Topic :: Utilities
Requires-Dist: gitpython>=3.1.40
Requires-Dist: click>=8.1.7
Requires-Dist: rich>=13.7.0
Requires-Dist: pytest>=7.4.0 ; extra == 'dev'
Requires-Dist: pytest-cov>=4.1.0 ; extra == 'dev'
Maintainer: Ashalesh Tilawat
Maintainer-email: Ashalesh Tilawat <ashtilawat23@gmail.com>
Requires-Python: >=3.9
Project-URL: Bug Tracker, https://github.com/ashtilawat23/merge-guard/issues
Project-URL: Changelog, https://github.com/ashtilawat23/merge-guard/blob/main/CHANGELOG.md
Project-URL: Documentation, https://github.com/ashtilawat23/merge-guard#readme
Project-URL: Homepage, https://github.com/ashtilawat23/merge-guard
Project-URL: Repository, https://github.com/ashtilawat23/merge-guard
Provides-Extra: dev
